README.md
setup.cfg
setup.py
crowdai_api/__init__.py
crowdai_api/crowdai_api.py
crowdai_api/events.py
crowdai_api/exceptions.py
crowdai_api/gitlab_submission.py
crowdai_api/helpers.py
crowdai_api/submission.py
crowdai_api.egg-info/PKG-INFO
crowdai_api.egg-info/SOURCES.txt
crowdai_api.egg-info/dependency_links.txt
crowdai_api.egg-info/not-zip-safe
crowdai_api.egg-info/pbr.json
crowdai_api.egg-info/requires.txt
crowdai_api.egg-info/top_level.txt