Metadata-Version: 1.1
Name: crowdai-api
Version: 0.1.18
Summary: python api for interacting with crowdAI grading infrastructure
Home-page: https://github.com/crowdai/crowdai_api
Author: S.P. Mohanty
Author-email: spmohanty91@gmail.com
License: GNU General Public License v3
Keywords: crowdai_api crowdai
Platform: UNKNOWN
Classifier: Development Status :: 2 - Pre-Alpha
Classifier: Intended Audience :: Developers
Classifier: License :: OSI Approved :: GNU General Public License v3 (GPLv3)
Classifier: Natural Language :: English
Classifier: Programming Language :: Python :: 2
Classifier: Programming Language :: Python :: 2.7
Classifier: Programming Language :: Python :: 3
Classifier: Programming Language :: Python :: 3.4
Classifier: Programming Language :: Python :: 3.5
Classifier: Programming Language :: Python :: 3.6
